Metadata-Version: 2.4
Name: sciglob
Version: 0.1.4
Summary: Python library for controlling SciGlob scientific instrumentation: Head Sensors, Trackers, Filter Wheels, and more
Author-email: Ashutosh Joshi <ajoshi@sciglob.com>
Maintainer-email: Ashutosh Joshi <ajoshi@sciglob.com>
License: MIT
Project-URL: Homepage, https://github.com/ashutoshjoshi1/SciGlob-Library
Project-URL: Documentation, https://github.com/ashutoshjoshi1/SciGlob-Library/blob/main/docs/API_REFERENCE.md
Project-URL: Repository, https://github.com/ashutoshjoshi1/SciGlob-Library.git
Project-URL: Issues, https://github.com/ashutoshjoshi1/SciGlob-Library/issues
Project-URL: Changelog, https://github.com/ashutoshjoshi1/SciGlob-Library/blob/main/CHANGELOG.md
Keywords: scientific-instrumentation,sensor-head,filter-wheel,tracker,motor-control,azimuth,zenith,atmospheric-monitoring,spectrometer,serial-communication,hardware-control
Classifier: Development Status :: 4 - Beta
Classifier: Intended Audience :: Science/Research
Classifier: Intended Audience :: Developers
Classifier: License :: OSI Approved :: MIT License
Classifier: Operating System :: OS Independent
Classifier: Operating System :: POSIX :: Linux
Classifier: Operating System :: Microsoft :: Windows
Classifier: Operating System :: MacOS
Classifier: Programming Language :: Python :: 3
Classifier: Programming Language :: Python :: 3.9
Classifier: Programming Language :: Python :: 3.10
Classifier: Programming Language :: Python :: 3.11
Classifier: Programming Language :: Python :: 3.12
Classifier: Topic :: Scientific/Engineering
Classifier: Topic :: Scientific/Engineering :: Atmospheric Science
Classifier: Topic :: Scientific/Engineering :: Physics
Classifier: Topic :: System :: Hardware
Classifier: Topic :: System :: Hardware :: Hardware Drivers
Classifier: Typing :: Typed
Requires-Python: >=3.9
License-File: LICENSE
Requires-Dist: pyserial>=3.5
Requires-Dist: pyyaml>=6.0
Provides-Extra: dev
Requires-Dist: pytest>=7.0; extra == "dev"
Requires-Dist: pytest-cov>=4.0; extra == "dev"
Requires-Dist: pytest-mock>=3.10; extra == "dev"
Requires-Dist: black>=23.0; extra == "dev"
Requires-Dist: ruff>=0.1.0; extra == "dev"
Requires-Dist: mypy>=1.0; extra == "dev"
Requires-Dist: isort>=5.12; extra == "dev"
Requires-Dist: pre-commit>=3.0; extra == "dev"
Requires-Dist: build>=1.0; extra == "dev"
Requires-Dist: twine>=4.0; extra == "dev"
Provides-Extra: docs
Requires-Dist: mkdocs>=1.5; extra == "docs"
Requires-Dist: mkdocs-material>=9.0; extra == "docs"
Requires-Dist: mkdocstrings[python]>=0.24; extra == "docs"
Provides-Extra: all
Requires-Dist: sciglob[dev,docs]; extra == "all"
Dynamic: license-file
